BibliotecaNumericaG2/__init__.py
BibliotecaNumericaG2/aproximacao/__init__.py
BibliotecaNumericaG2/aproximacao/ajuste_polinomial_min_quadrados.py
BibliotecaNumericaG2/aproximacao/minimos_quadrados.py
BibliotecaNumericaG2/aproximacao/theil_sen.py
BibliotecaNumericaG2/aproximacao/plotagem/__init__.py
BibliotecaNumericaG2/aproximacao/plotagem/plot_linear_minimos_quadrados.py
BibliotecaNumericaG2/aproximacao/plotagem/plot_linear_theil_sen.py
BibliotecaNumericaG2/aproximacao/plotagem/plot_polinomio_minimos_quadrados.py
BibliotecaNumericaG2/erros/__init__.py
BibliotecaNumericaG2/erros/erro_absoluto.py
BibliotecaNumericaG2/erros/erro_relativo.py
BibliotecaNumericaG2/integracao/__init__.py
BibliotecaNumericaG2/integracao/integracao_componentes.py
BibliotecaNumericaG2/integracao/integracao_retangulo.py
BibliotecaNumericaG2/integracao/integracao_trapezio.py
BibliotecaNumericaG2/interpolacao/__init__.py
BibliotecaNumericaG2/interpolacao/interpolacao_hermite.py
BibliotecaNumericaG2/interpolacao/interpolacao_polinomial.py
BibliotecaNumericaG2/interpolacao/linear.py
BibliotecaNumericaG2/interpolacao/linear_partes.py
BibliotecaNumericaG2/raizes/__init__.py
BibliotecaNumericaG2/raizes/bisseccao.py
BibliotecaNumericaG2/raizes/newton_raphson.py
BibliotecaNumericaG2/raizes/secante.py
bibliotecanumericag2-0.0.8.dist-info/licenses/LICENSE
bibliotecanumericag2-0.0.8.dist-info/METADATA
bibliotecanumericag2-0.0.8.dist-info/WHEEL
bibliotecanumericag2-0.0.8.dist-info/top_level.txt
bibliotecanumericag2-0.0.8.dist-info/RECORD
